xarr/__init__.py
xarr/_modidx.py
xarr/core.py
xarr-0.0.1.dist-info/LICENSE
xarr-0.0.1.dist-info/METADATA
xarr-0.0.1.dist-info/WHEEL
xarr-0.0.1.dist-info/entry_points.txt
xarr-0.0.1.dist-info/top_level.txt
xarr-0.0.1.dist-info/RECORD
