Metadata-Version: 2.1
Name: xarr
Version: 0.0.1
Summary: xarr
Home-page: https://github.com/dsm-72/xarr
Author: dsm-72
Author-email: sumner.magruder@yale.edu
License: Apache Software License 2.0
Keywords: as to convert from one type another
Classifier: Development Status :: 4 - Beta
Classifier: Intended Audience :: Developers
Classifier: Natural Language :: English
Classifier: Programming Language :: Python :: 3.11
Classifier: License :: OSI Approved :: Apache Software License
Requires-Python: >=3.11
License-File: LICENSE
Requires-Dist: atyp
Requires-Dist: nchr
Requires-Dist: nlit
Requires-Dist: chck
Requires-Dist: idfunc
Requires-Dist: acall
Requires-Dist: ain
Requires-Dist: mstar
Requires-Dist: numpy >=1.22
Provides-Extra: dev
Requires-Dist: numpy >=1.22 ; extra == 'dev'
